Metadata-Version: 2.1
Name: sage-spelling
Version: 1.1.0
Summary: SAGE: Spell checking via Augmentation and  Generative distribution Emulation
Home-page: https://github.com/orgs/ai-forever/sage
Author: Nikita Martynov, Mark Baushenko, Alena Fenogenova and Alexandr Abramov
Author-email: nikita.martynov.98@list.ru
License: MIT
Keywords: sage spelling correction nlp deep learning transformers pytorch
Classifier: Natural Language :: English
Classifier: Natural Language :: Russian
Classifier: Programming Language :: Python :: 3.8
Classifier: Programming Language :: Python :: 3.9
Classifier: Programming Language :: Python :: 3.10
Classifier: Topic :: Scientific/Engineering :: Artificial Intelligence
Classifier: Topic :: Software Development :: Libraries :: Python Modules
Classifier: Topic :: Text Editors :: Text Processing
Requires-Python: >=3.8.0,<=3.12.3
License-File: LICENSE
Requires-Dist: numpy
Requires-Dist: pandas
Requires-Dist: tqdm
Requires-Dist: pyyaml
Requires-Dist: packaging
Requires-Dist: requests
Requires-Dist: sentencepiece
Requires-Dist: datasets <2.20.0
Requires-Dist: protobuf
Requires-Dist: timeout-decorator
Requires-Dist: matplotlib <3.7,>=3.2
Requires-Dist: torch <=2.2.0,>=1.9.0
Requires-Dist: transformers >=4.20.0
Requires-Dist: augmentex ==1.3.1
Provides-Extra: errant
Requires-Dist: ru-errant ; extra == 'errant'
Requires-Dist: spacy <3.8.0,>=3.7.0 ; extra == 'errant'
Requires-Dist: Levenshtein ; extra == 'errant'
